incuna_videos-7.0.0.dist-info/DESCRIPTION.rst
incuna_videos-7.0.0.dist-info/METADATA
incuna_videos-7.0.0.dist-info/RECORD
incuna_videos-7.0.0.dist-info/WHEEL
incuna_videos-7.0.0.dist-info/metadata.json
incuna_videos-7.0.0.dist-info/top_level.txt
videos/__init__.py
videos/admin.py
videos/content.py
videos/models.py
videos/urls.py
videos/views.py
videos/extensions/__init__.py
videos/extensions/captions.py
videos/extensions/chapters.py
videos/extensions/speakers.py
videos/extensions/sub_heading.py
videos/module/__init__.py
videos/module/chapters/__init__.py
videos/module/chapters/models.py
videos/module/chapters/tests/__init__.py
videos/module/chapters/tests/factories.py
videos/module/chapters/tests/test_models.py
videos/module/speakers/__init__.py
videos/module/speakers/admin.py
videos/module/speakers/models.py
videos/module/speakers/tests/__init__.py
videos/module/speakers/tests/factories.py
videos/module/speakers/tests/test_models.py
videos/templates/videos/_video.html
videos/templates/videos/base.html
videos/templates/videos/detail.html
videos/templates/videos/list.html
videos/templates/videos/content/default.html
videos/tests/__init__.py
videos/tests/factories.py
videos/tests/models.py
videos/tests/run.py
videos/tests/test_content.py
videos/tests/test_models.py
videos/tests/test_urls.py
videos/tests/test_views.py
videos/tests/urls.py
