Metadata-Version: 2.0
Name: incuna-videos
Version: 7.0.0
Summary: Generic extensible video content.
Home-page: https://github.com/incuna/incuna-videos
Author: Incuna Ltd
Author-email: admin@incuna.com
License: UNKNOWN
Platform: UNKNOWN
Requires-Dist: FeinCMS (>=1.11,<1.12)
Requires-Dist: django-imagekit (<3.4,>=3.3)
